{
  "resource_state": 2,
  "athlete": {
    "id": 10920812,
    "resource_state": 1
  },
  "name": "晨間跑步",
  "distance": 9014.3,
  "moving_time": 3504,
  "elapsed_time": 3714,
  "total_elevation_gain": 4.0,
  "type": "Run",
  "sport_type": "Run",
  "workout_type": null,
  "device_name": "Garmin Forerunner 255",
  "id": 11388895729,
  "start_date": "2024-05-11T22:03:43Z",
  "start_date_local": "2024-05-12T06:03:43Z",
  "timezone": "(GMT+08:00) Asia/Shanghai",
  "utc_offset": 28800.0,
  "location_city": null,
  "location_state": null,
  "location_country": null,
  "achievement_count": 0,
  "kudos_count": 0,
  "comment_count": 0,
  "athlete_count": 1,
  "photo_count": 0,
  "map": {
    "id": "a11388895729",
    "summary_polyline": "gxs~DomhxU]BgBD[CuBJq@?YBIA?CzAAhAGnA?rAK\\?\\G~@CXKTMV[HOXSJ]By@Ao@FaAF[@sAFq@DsAHe@?SJkAA`AQlDAhACb@Ih@?TE\\@x@Ip@Bl@BRFJ?FKUEc@DeAA{@LiBJkDFm@DgAJkA?}@Fq@?c@Du@NkABqBLoARkATk@DEPIjAOb@MrBa@l@E~Ci@nAOhB]nDc@b@Kt@K\\I|AOr@E~@AzBH`ALdBJNDZZHRD\\E`AAlAEf@?tAIx@I|BKpEQbEAjASdFOpB?l@Eh@I\\QPGFSBcBDYDy@?y@B_B?[EgBB_AG]?q@EmADe@E[BsABk@HmG@cADqAK[@_AE]?SAQSIQIa@CaANiCDcBBw@Hk@BoAHgANaD@c@Fg@JyAB{@Ag@`@oDJc@JQZK`Dq@RAJErAUh@En@OVArAW~@IjAWlBUlB_@n@Ej@KdAKZ?dAIrA?tCT`@Hf@BLBZPJLN^@JI|AEvDEXIlAEnCWrHSjB?\\Bv@GhBAx@QzBAp@EXEJUTGBo@Dw@Au@Jw@Ay@Do@IoADs@EaA@k@Gi@Ce@?_@Bi@?[Es@Hw@@_BHaA?_@Cc@BaDBs@Ey@?a@Gg@?]GSKIOGWEaABu@JuA@cBF_@FmA@s@LqBBW@ADWNM^Ot@Gz@SZCv@MtB_@bC]^I|@Ih@AtCNPJFJ?LQhEGzBMlBC|AG`AAZQzAOb@]`@QF_A?k@FuBHcBAcABWC_A@{@Ea@@g@G{@AUIIIKUKm@JgE",
    "resource_state": 2
  },
  "trainer": false,
  "commute": false,
  "manual": false,
  "private": false,
  "visibility": "followers_only",
  "flagged": false,
  "gear_id": null,
  "start_latlng": [
    31.39898437075317,
    119.48857840150595
  ],
  "end_latlng": [
    31.398643478751183,
    119.49055200442672
  ],
  "average_speed": 2.573,
  "max_speed": 3.34,
  "average_cadence": 91.9,
  "average_temp": 22,
  "average_watts": 267.7,
  "max_watts": 316,
  "weighted_average_watts": 261,
  "device_watts": true,
  "kilojoules": 935.1,
  "has_heartrate": true,
  "average_heartrate": 141.9,
  "max_heartrate": 165.0,
  "heartrate_opt_out": false,
  "display_hide_heartrate_option": true,
  "elev_high": 6.6,
  "elev_low": -2.6,
  "upload_id": 12162445813,
  "upload_id_str": "12162445813",
  "external_id": "garmin_ping_339836048166",
  "from_accepted_tag": false,
  "pr_count": 0,
  "total_photo_count": 0,
  "has_kudoed": false
}