{
  "resource_state": 2,
  "athlete": {
    "id": 10920812,
    "resource_state": 1
  },
  "name": "午後跑步",
  "distance": 8008.2,
  "moving_time": 3428,
  "elapsed_time": 4090,
  "total_elevation_gain": 18.0,
  "type": "Run",
  "sport_type": "Run",
  "workout_type": null,
  "device_name": "Garmin Forerunner 255",
  "id": 11852929616,
  "start_date": "2024-07-10T09:30:43Z",
  "start_date_local": "2024-07-10T17:30:43Z",
  "timezone": "(GMT+08:00) Asia/Shanghai",
  "utc_offset": 28800.0,
  "location_city": null,
  "location_state": null,
  "location_country": null,
  "achievement_count": 0,
  "kudos_count": 0,
  "comment_count": 0,
  "athlete_count": 1,
  "photo_count": 0,
  "map": {
    "id": "a11852929616",
    "summary_polyline": "uds~DgxixUf@GzCi@vAOnAY^C~@Kh@Kf@G^K\\Az@O|AM@Ix@Eb@?ZDtADrAJ~@Lh@Bd@XVj@@RGp@OhFOlD?ZC`@QjHQvAD~AOdC@b@G~@E`@CfAKf@Eh@?n@Cj@@~@Ez@BtAIlDEX?l@Gn@EbBKhCQl@ARE~B?CHVATKzCIjDObBCh@DjAAp@KzAErBSbAC~@Eb@@LJb@KvBQhHWpGI\\[j@QNYDqBR_APw@F[HO?g@LMCiAPyBNiAN}@FIAe@Hi@Dy@RcBNk@LgALM?{@PkA@YFuDf@iCTKCQGKKISAWB_@?eALgBFeBHIBS@c@RwCB{@NiC?s@PsBLcDBMAe@JcFLcA@{@PsB?a@Jc@D{@A]Hi@FgBHs@@u@Js@FaAF}AAs@D_DH{@@g@Fm@@}@D}@Fs@H_@Dc@J_BNqABoAJ}@Ca@@gABs@AkARqC?w@CDHGNaD@w@DG@[AaBJuANyA?gBHk@Bo@Lq@Nk@HO\\Ox@MNGhB_@rEu@bAKvEu@^CTHDFFN?LE@@p@GnBMvCGn@?z@WjHIxAIjCUrECfAIhAKr@Wf@KLSJYDi@?kAHeBAs@Bc@F{@CcB@iAAi@IcA?WMKOQe@Ec@@m@FaBBcCJ{@D_CP{AFcB",
    "resource_state": 2
  },
  "trainer": false,
  "commute": false,
  "manual": false,
  "private": false,
  "visibility": "followers_only",
  "flagged": false,
  "gear_id": null,
  "start_latlng": [
    31.398432590067387,
    119.49290874414146
  ],
  "end_latlng": [
    31.398453125730157,
    119.49285526759923
  ],
  "average_speed": 2.336,
  "max_speed": 3.21,
  "average_cadence": 87.7,
  "average_temp": 30,
  "average_watts": 250.3,
  "max_watts": 335,
  "weighted_average_watts": 231,
  "device_watts": true,
  "kilojoules": 854.1,
  "has_heartrate": true,
  "average_heartrate": 139.5,
  "max_heartrate": 156.0,
  "heartrate_opt_out": false,
  "display_hide_heartrate_option": true,
  "elev_high": 21.2,
  "elev_low": 5.4,
  "upload_id": 12640510636,
  "upload_id_str": "12640510636",
  "external_id": "garmin_ping_353876796124",
  "from_accepted_tag": false,
  "pr_count": 0,
  "total_photo_count": 0,
  "has_kudoed": false
}