{
  "resource_state": 2,
  "athlete": {
    "id": 10920812,
    "resource_state": 1
  },
  "name": "傍晚鍛鍊",
  "distance": 0.0,
  "moving_time": 322,
  "elapsed_time": 322,
  "total_elevation_gain": 0,
  "type": "Workout",
  "sport_type": "Workout",
  "workout_type": null,
  "device_name": "Apple Watch Ultra 2",
  "id": 12168435494,
  "start_date": "2024-07-26T11:29:58Z",
  "start_date_local": "2024-07-26T19:29:58Z",
  "timezone": "(GMT+08:00) Antarctica/Casey",
  "utc_offset": 28800.0,
  "location_city": null,
  "location_state": null,
  "location_country": null,
  "achievement_count": 0,
  "kudos_count": 0,
  "comment_count": 0,
  "athlete_count": 1,
  "photo_count": 0,
  "map": {
    "id": "a12168435494",
    "summary_polyline": "",
    "resource_state": 2
  },
  "trainer": true,
  "commute": false,
  "manual": false,
  "private": false,
  "visibility": "followers_only",
  "flagged": false,
  "gear_id": null,
  "start_latlng": [],
  "end_latlng": [],
  "average_speed": 0.0,
  "max_speed": 0.0,
  "has_heartrate": true,
  "average_heartrate": 61.5,
  "max_heartrate": 76.0,
  "heartrate_opt_out": false,
  "display_hide_heartrate_option": true,
  "elev_high": 0.0,
  "elev_low": 0.0,
  "upload_id": 12971769871,
  "upload_id_str": "12971769871",
  "external_id": "CB0DC16E-2F7D-484E-8C2C-25A0705D2E82.fit",
  "from_accepted_tag": false,
  "pr_count": 0,
  "total_photo_count": 0,
  "has_kudoed": false
}