{
  "resource_state": 2,
  "athlete": {
    "id": 10920812,
    "resource_state": 1
  },
  "name": "晨間步行",
  "distance": 2678.1,
  "moving_time": 2104,
  "elapsed_time": 2166,
  "total_elevation_gain": 7.2,
  "type": "Walk",
  "sport_type": "Walk",
  "device_name": "Apple Watch Ultra 2",
  "id": 12437240776,
  "start_date": "2024-09-15T23:28:25Z",
  "start_date_local": "2024-09-16T07:28:25Z",
  "timezone": "(GMT+08:00) Asia/Shanghai",
  "utc_offset": 28800.0,
  "location_city": null,
  "location_state": null,
  "location_country": null,
  "achievement_count": 0,
  "kudos_count": 0,
  "comment_count": 0,
  "athlete_count": 1,
  "photo_count": 0,
  "map": {
    "id": "a12437240776",
    "summary_polyline": "{|u~D{fhxUW?[F}@AQCgAJOCOQAm@By@L[BM?]JeABg@BKFGfBCrCM\\@t@ABFCf@BxAEz@BLCBMBiADMA?C]D_B@c@B[E[B]?KCEGCMJWA]LwBBMFCrDKv@BTEVDr@EF@Ax@Bp@ChBSDc@?YB[CYB{BDm@Ce@BMAKGCOJYAYFy@Dg@@[DIpEI\\ARE`@@b@AJ@@BAl@BbAEl@Bh@ABEDYB{A?OBy@AeADSCy@BUIEMJ_@?e@NsBHEfCC",
    "resource_state": 2
  },
  "trainer": false,
  "commute": false,
  "manual": false,
  "private": false,
  "visibility": "followers_only",
  "flagged": false,
  "gear_id": null,
  "start_latlng": [
    31.409475663676858,
    119.48675701394677
  ],
  "end_latlng": [
    31.409655204042792,
    119.4880108628422
  ],
  "average_speed": 1.273,
  "max_speed": 2.436,
  "has_heartrate": true,
  "average_heartrate": 90.6,
  "max_heartrate": 99.0,
  "heartrate_opt_out": false,
  "display_hide_heartrate_option": true,
  "elev_high": 8.6,
  "elev_low": 5.5,
  "upload_id": 13260286851,
  "upload_id_str": "13260286851",
  "external_id": "73C1ABE0-8875-4A84-8F75-9F801B41F3ED.fit",
  "from_accepted_tag": false,
  "pr_count": 0,
  "total_photo_count": 0,
  "has_kudoed": false
}