{
  "resource_state": 2,
  "athlete": {
    "id": 10920812,
    "resource_state": 1
  },
  "name": "Nike Run Club: 星期六早上路跑",
  "distance": 12011.8,
  "moving_time": 4439,
  "elapsed_time": 4957,
  "total_elevation_gain": 16.0,
  "type": "Run",
  "sport_type": "Run",
  "workout_type": null,
  "device_name": "Nike",
  "id": 12800311833,
  "start_date": "2024-11-01T21:41:46Z",
  "start_date_local": "2024-11-02T05:41:46Z",
  "timezone": "(GMT+08:00) Asia/Shanghai",
  "utc_offset": 28800.0,
  "location_city": null,
  "location_state": null,
  "location_country": null,
  "achievement_count": 0,
  "kudos_count": 0,
  "comment_count": 0,
  "athlete_count": 1,
  "photo_count": 0,
  "map": {
    "id": "a12800311833",
    "summary_polyline": "q{t~D_kixUAl@GdA?p@IdACxAKtB@XOtBCxBGl@EfA?r@MzA?XPJb@?f@GrBBtAIf@@f@EtAARGvAATBNER?z@?z@Ch@@NGT?PDvBERC~A?~@Kh@@f@I|BKd@Bf@C`A@pANnAGtADx@ApABf@Ef@Bf@ER@j@IfBIP?x@Fj@CTBx@?|@Fd@APBj@@f@CrA@PCpA?rAKPBf@GT?RQJOFo@H{AHk@@YAq@JuB@uBJyADwBBYNmFDm@FcDHeB?iA@WAYGSKSe@UwAOoAIUCmAEaB@c@Dg@Be@DwB`@i@Bc@LcBRQJi@BiBVUFe@F{@NW@uB\\QFS@QDgA^i@HS?c@NKPGRUnBIdACtBMl@MrBGxBIbACfAMxA@TETCdAKpBE|ANbALVLLTDv@@TBh@@f@Cd@@f@A|@Df@Ad@BRARBf@IRBP?~@Kf@ARGTBf@Gf@Hf@?TCxBHjD@~@Bf@Cd@@j@IdBA|@EPIJOLk@VcE?m@J_BB}BJsB?UDgBDk@?ULuBCYFo@B}AAm@FeAHeCAs@Mi@QQQIUCe@CSEpAFTJPPPh@BTER[hKIvA?~ACn@El@GxBMdAEp@B~ACVIjCMzA@TEVAl@IRKLUDoA@y@JwADkC?aAESDuBKU@y@GUDgBAi@Fg@Ae@DSASFWCUBqAA_ACcBDSAS@g@EsA?y@GQIWg@GcBHuBDUDiAFm@@iAHq@BiANiC?UJyBPmB?gADm@RqBRk@JQPIRCPGf@EPEPK~AYRAnAWpAOjCc@nBSv@Sh@C|Ci@lC[h@@fBCnALz@Fh@Jh@@b@TLLHTFX@ZMpEIpBAj@GfAA|AEj@I~CEdASzA?l@Bp@En@AxAKzAETE~ACTIPONSHi@AUBy@@}@Dg@?QBSAsC@sAC_AIoB@SA_A?eABiBN_AEQByAAe@@aA?i@Bg@Ey@@SIg@@_AGqABQG{@Hi@BSHi@A}@FUAUBg@E{@JUAg@Fk@Ce@BWAoCHW?SEWDe@A}@H_A@UBaA?SBQKOUAYDWD_BDY@o@BW?mAF_B?iANwB?q@BWDaBLsCEYDk@AUKOSGsBf@uALc@R@u@Cu@",
    "resource_state": 2
  },
  "trainer": false,
  "commute": false,
  "manual": false,
  "private": false,
  "visibility": "followers_only",
  "flagged": false,
  "gear_id": null,
  "start_latlng": [
    31.405425,
    119.493875
  ],
  "end_latlng": [
    31.405401,
    119.49446
  ],
  "average_speed": 2.706,
  "max_speed": 3.54,
  "average_cadence": 92.3,
  "has_heartrate": true,
  "average_heartrate": 148.8,
  "max_heartrate": 174.0,
  "heartrate_opt_out": false,
  "display_hide_heartrate_option": true,
  "elev_high": 13.4,
  "elev_low": 3.6,
  "upload_id": 13648723504,
  "upload_id_str": "13648723504",
  "external_id": "87aba2b7-027d-49e7-8144-ea13bb53de1a.fit",
  "from_accepted_tag": false,
  "pr_count": 0,
  "total_photo_count": 0,
  "has_kudoed": false
}