{
  "resource_state": 2,
  "athlete": {
    "id": 10920812,
    "resource_state": 1
  },
  "name": "Nike Run Club: 星期五早上路跑",
  "distance": 7336.8,
  "moving_time": 3035,
  "elapsed_time": 3065,
  "total_elevation_gain": 17.0,
  "type": "Run",
  "sport_type": "Run",
  "workout_type": null,
  "device_name": "Nike",
  "id": 12902688117,
  "start_date": "2024-11-14T22:38:28Z",
  "start_date_local": "2024-11-15T06:38:28Z",
  "timezone": "(GMT+08:00) Asia/Shanghai",
  "utc_offset": 28800.0,
  "location_city": null,
  "location_state": null,
  "location_country": null,
  "achievement_count": 0,
  "kudos_count": 0,
  "comment_count": 0,
  "athlete_count": 2,
  "photo_count": 0,
  "map": {
    "id": "a12902688117",
    "summary_polyline": "wpt~DwkhxUxBIf@@hCKh@@j@IT@RDTBhBCh@Id@A|@DPEV@PCPERCh@@nAKjC@TDl@Bf@?PGNHT@lCCTBbBGz@BnACTGd@?`AGj@DPAbC@`BF`AARBrABt@Eh@@b@ERBpA@f@Kh@s@FY@cADY?[DWAYNoEBk@BUAi@FgAAWJgA?q@H{ADeDLyA@UAYDWCWDgA?m@FgAAi@Sg@e@WQGU?mAQi@AQEU@e@Ge@@SC}@A}@Le@BwEr@k@BoAZwBZSCQHe@Jw@FQHw@JS?cB^Q?QJwB`@e@RKPMf@UzAEj@IrCGl@Cn@ERE|BQ|AEtBKjA@l@Il@Al@BZIn@BRETGn@@p@Tj@LNh@Hh@DR@|@APDRA|@Hh@Gz@?j@C~@@PAd@DRANIRBPAj@?lAK~@?d@BrABf@BRCf@DdBATBx@@`BENER?RFT@RER@ZE`@[Ze@Fq@J_BHUBgDCaADeAJq@?UBUAUBUNuBAW@U?kABUAk@BY?YJ_BFUHQIeA?o@Dm@AUJ{AQe@MOOMQCk@C}@I}AWi@ASEy@@SEw@FSDUASLoAFg@HSJe@JOFsALQDi@BQFS?e@Ji@@k@JQJSBUAOJQDsANQHUAaEv@c@LaBVQDOJSBQCU?i@FQ?i@JQ?UHUAS@e@LU?i@Fe@LwB^MMUA{@b@{@JUNUDsAFUFi@Fk@@e@Hk@PwATULi@?mAPOJy@VUDe@ASBQJKP",
    "resource_state": 2
  },
  "trainer": false,
  "commute": false,
  "manual": false,
  "private": false,
  "visibility": "followers_only",
  "flagged": false,
  "gear_id": null,
  "start_latlng": [
    31.405987,
    119.487414
  ],
  "end_latlng": [
    31.405908,
    119.48958
  ],
  "average_speed": 2.417,
  "max_speed": 4.92,
  "average_cadence": 89.5,
  "has_heartrate": true,
  "average_heartrate": 126.9,
  "max_heartrate": 127.0,
  "heartrate_opt_out": false,
  "display_hide_heartrate_option": true,
  "elev_high": 10.8,
  "elev_low": 2.4,
  "upload_id": 13758696450,
  "upload_id_str": "13758696450",
  "external_id": "af5ac189-2673-4743-837b-4b35de4bc96e.fit",
  "from_accepted_tag": false,
  "pr_count": 0,
  "total_photo_count": 0,
  "has_kudoed": false
}