{
  "resource_state": 2,
  "athlete": {
    "id": 10920812,
    "resource_state": 1
  },
  "name": "午后行走",
  "distance": 3104.7,
  "moving_time": 2803,
  "elapsed_time": 3143,
  "total_elevation_gain": 53.6,
  "type": "Walk",
  "sport_type": "Walk",
  "device_name": "Apple Watch Ultra 2",
  "id": 13490093666,
  "start_date": "2025-01-29T05:17:00Z",
  "start_date_local": "2025-01-29T13:17:00Z",
  "timezone": "(GMT+08:00) Asia/Shanghai",
  "utc_offset": 28800.0,
  "location_city": null,
  "location_state": null,
  "location_country": null,
  "achievement_count": 0,
  "kudos_count": 0,
  "comment_count": 0,
  "athlete_count": 1,
  "photo_count": 0,
  "map": {
    "id": "a13490093666",
    "summary_polyline": "sor~DkihxUo@Be@Gw@Bm@E_@KO?WSu@CIMBcBVmBJgBLwDVgF@gAFkAAIGG_BKiBAgALmCb@JNNH`@@JDLXb@d@F?POB?HDZd@RCHBOAQ@QS?HOPMd@g@LQXc@RQZUFMJCFQBCE?IIKEk@BYAES[QEW?UKQSKOCYKQCSgAJgAPMCMWCK?[HgBPcB?u@AUXoCYOg@GUMWGs@H]?m@Ha@@iAVU@ODa@Be@LSAa@Hq@P]@kBZk@FSJkEl@iAVc@BiAPk@BSCqCf@gALUH_@FECBy@D_@H{BAkADe@M_@ME",
    "resource_state": 2
  },
  "trainer": false,
  "commute": false,
  "manual": false,
  "private": false,
  "visibility": "followers_only",
  "flagged": false,
  "gear_id": null,
  "start_latlng": [
    31.391962,
    119.486469
  ],
  "end_latlng": [
    31.407261,
    119.494764
  ],
  "average_speed": 1.108,
  "max_speed": 2.313,
  "has_heartrate": true,
  "average_heartrate": 110.8,
  "max_heartrate": 127.0,
  "heartrate_opt_out": false,
  "display_hide_heartrate_option": true,
  "elev_high": 17.8,
  "elev_low": 3.0,
  "upload_id": 14390330377,
  "upload_id_str": "14390330377",
  "external_id": "1724B170-394C-4254-85D0-5AFF431DB660.fit",
  "from_accepted_tag": false,
  "pr_count": 0,
  "total_photo_count": 0,
  "has_kudoed": false
}