{
  "resource_state": 2,
  "athlete": {
    "id": 10920812,
    "resource_state": 1
  },
  "name": "晨间远足",
  "distance": 4769.5,
  "moving_time": 3450,
  "elapsed_time": 4584,
  "total_elevation_gain": 44.0,
  "type": "Hike",
  "sport_type": "Hike",
  "device_name": "Apple Watch Ultra 2",
  "id": 13551785642,
  "start_date": "2025-02-05T23:19:50Z",
  "start_date_local": "2025-02-06T07:19:50Z",
  "timezone": "(GMT+08:00) Asia/Shanghai",
  "utc_offset": 28800.0,
  "location_city": null,
  "location_state": null,
  "location_country": null,
  "achievement_count": 0,
  "kudos_count": 0,
  "comment_count": 0,
  "athlete_count": 1,
  "photo_count": 0,
  "map": {
    "id": "a13551785642",
    "summary_polyline": "q}t~DaajxUdBGN@FFMbEGn@GfCQjE?T@FZMd@EFG\\?jCc@JEd@[DAJHH?j@Mh@Gn@Q\\SZIPCjA@fBYh@Gv@Qj@@p@SxB[h@KdAK~A[^Mb@Ir@Yp@Jj@IL@HJCf@@LHRLNTG?BJEhDu@bBYT?BB@H_@~H@P?b@HPBVGfA@TF`@LJFZ^`@NHl@bAFPRIJ@LBNNHR?PEZA@A?HSTE?SFIRGD@BDH`@ChAFrAENF^?TE~@U|@IH]Ja@X_@Pk@Ae@RU?QB[LQEUJKBiA@k@Gg@a@YIQg@[g@OKsAJSCa@Wc@BMFS^ElASjA[l@ONSJ{@Dy@JwBJwDBWBMAu@Fg@AuBB_@AyBD_@CKEGIW_@IWB_@CkAYlBQ@MEKKGOIKCAIBEEEGAM@QJa@G[DU?i@H[Cc@@g@FYAYDi@?i@Dq@FWEi@F[@m@Fc@C]Bo@Hg@Ei@D[?WJi@EUGEMCcFt@EAAGCcAGA_@La@BsAT}@JcAPgC\\{@PO@ECEG?OVyDFm@",
    "resource_state": 2
  },
  "trainer": false,
  "commute": false,
  "manual": false,
  "private": false,
  "visibility": "followers_only",
  "flagged": false,
  "gear_id": null,
  "start_latlng": [
    31.407632,
    119.495204
  ],
  "end_latlng": [
    31.407655,
    119.495128
  ],
  "average_speed": 1.382,
  "max_speed": 3.482,
  "has_heartrate": true,
  "average_heartrate": 82.7,
  "max_heartrate": 110.0,
  "heartrate_opt_out": false,
  "display_hide_heartrate_option": true,
  "elev_high": 14.4,
  "elev_low": 4.4,
  "upload_id": 14457726384,
  "upload_id_str": "14457726384",
  "external_id": "C43F4888-C3CC-4242-B84D-97EAA82C80A3.fit",
  "from_accepted_tag": false,
  "pr_count": 0,
  "total_photo_count": 0,
  "has_kudoed": false
}