{
  "resource_state": 2,
  "athlete": {
    "id": 10920812,
    "resource_state": 1
  },
  "name": "晨間跑步",
  "distance": 9405.1,
  "moving_time": 3628,
  "elapsed_time": 3994,
  "total_elevation_gain": 30.4,
  "type": "Run",
  "sport_type": "Run",
  "workout_type": null,
  "id": 17796644584,
  "start_date": "2026-03-20T22:10:38Z",
  "start_date_local": "2026-03-21T06:10:38Z",
  "timezone": "(GMT+08:00) Asia/Shanghai",
  "utc_offset": 28800.0,
  "location_city": null,
  "location_state": null,
  "location_country": null,
  "achievement_count": 0,
  "kudos_count": 0,
  "comment_count": 0,
  "athlete_count": 1,
  "photo_count": 0,
  "map": {
    "id": "a17796644584",
    "summary_polyline": "m{t~DemixU?j@If@{@nVIdACvBEf@BJHD|@CNCSFcA?GI?IDw@BsBJyAAz@OpETJx@?`@Gz@Dv@An@K`DE~AGdA?h@EdLMjAIrCM^KTMv@s@JQBM?aABi@LiBRoEXiEHkCPuB@uAJmAJg@Fm@Jc@JONGr@MbDq@|TgDpBUlAClABbCNlBRVNLPJ\\BVOrDGrCK~AEbCQvFCf@Kl@Ez@Dr@IjDKjAIjBCTMTWNu@Dk@@{@HkA@uBAkA@UCu@?s@Ew@?YEaABk@Co@BY?q@D_@AoAFmA@cFAsCI]MOSGWEsAb@kJHsA@s@Hu@DaBHyANyA@mADm@XqCJYJQXKf@GvCq@r@KjC]`ASnDi@h@EhF{@|AQ~@GbA?rBHhDZPHRPN\\DXQjDWdKStFO`BCv@BjAIlCMrACfAEf@GNMTQHsAAyBJmAAwBDyAC{@Gm@@i@C]D[@s@Ik@DmDJgE?]@oCCe@Cy@A_@EsAF_@Gm@He@@iALwFJW?}ADu@DcC@mADkDDkDP{B?aABIGESDa@BcARoDBmBd@{LV}E",
    "resource_state": 2
  },
  "trainer": false,
  "commute": false,
  "manual": false,
  "private": false,
  "visibility": "followers_only",
  "flagged": false,
  "gear_id": null,
  "start_latlng": [
    31.405412,
    119.49426
  ],
  "end_latlng": [
    31.405425,
    119.494212
  ],
  "average_speed": 2.592,
  "max_speed": 3.395,
  "has_heartrate": true,
  "average_heartrate": 133.2,
  "max_heartrate": 162.0,
  "heartrate_opt_out": false,
  "display_hide_heartrate_option": true,
  "elev_high": 11.9,
  "elev_low": 3.1,
  "upload_id": 18895711559,
  "upload_id_str": "18895711559",
  "external_id": "garmin_ping_548611106285",
  "from_accepted_tag": false,
  "pr_count": 0,
  "total_photo_count": 0,
  "has_kudoed": false
}