{
  "resource_state": 2,
  "athlete": {
    "id": 10920812,
    "resource_state": 1
  },
  "name": "晨間跑步",
  "distance": 9265.3,
  "moving_time": 3261,
  "elapsed_time": 3877,
  "total_elevation_gain": 122.0,
  "type": "Run",
  "sport_type": "Run",
  "workout_type": null,
  "id": 2660642258,
  "start_date": "2019-08-20T21:42:04Z",
  "start_date_local": "2019-08-21T05:42:04Z",
  "timezone": "(GMT+08:00) Asia/Shanghai",
  "utc_offset": 28800.0,
  "location_city": null,
  "location_state": null,
  "location_country": null,
  "achievement_count": 0,
  "kudos_count": 0,
  "comment_count": 0,
  "athlete_count": 1,
  "photo_count": 0,
  "map": {
    "id": "a2660642258",
    "summary_polyline": "qvz~DklgxU`CWj@?HC\\FXC^k@~@mA\\u@@GG_ABIB?ZTl@n@Pb@f@Zr@p@\\Vf@l@PND@h@j@vAlAv@d@d@JfCPTH`AB\\AXB\\?bAGXFZAVJl@Xf@d@z@h@RJRBZSVq@La@L_Ad@uBXo@HCZD^VlAjAf@^~AhBTFJ?Zd@LFTNT?\\EPYfAkDZoALOZBRAVKPcABEl@XMRGRCb@@LHTRTXH~@EvBGTOPc@D]Gc@SW]KkDXa@RS\\Cd@BTDJJJVNT@jAKt@?l@ERKP]D]Ca@MSe@SoDPIB_@\\K^?P@PNVZLfACbAGd@@^KJGHOHe@Ee@U[a@IcBNeAFSFMJMTGP?d@P^NH^@dAInAEd@IPSLi@Eg@MQYQYAm@HyBLYLOVCJAd@L\\LLFBX@rAKbA@NATGT[J[@KGc@Y[[Ku@HeAD{@H_@ZK\\@`@N^TLX?r@Gd@Cj@@f@GRKR[Fe@I_@_@[MCiDRUDURO\\@\\J^TNRBn@@lCQTSPe@@QCSU_@_@OgDL_@HHGPE^?h@GfACZ@RHIC}@?{AFo@HKFQRIZBd@JZVNX@fAGjA?d@IPOJ[@]?KOe@[Qa@AaCPc@H]ZGb@Fd@RXZDjAE|ACXITYHc@Ck@UW]KiALoBJMHSRGV@f@HZXJvBEbA@HCVOHQJ[Aa@Qc@]OeABkBRc@NOXAl@HTVRb@D`@Ed@AvA?`@MPe@Bc@Og@WWYCUD{@Fs@@m@F]XK\\@d@PVXP^@n@ErA?d@GVYLc@AYAKS_@]M}CLg@HUZEPCVD\\FRTHZ@xAGd@Bl@CZQNg@Ae@CMOSmGAUn@STc@ROA_@MCI@uAAgAEe@I]Ai@B_@A{@KuBG_@GeBKkABk@EOWC_AH[Aa@D]?c@Da@Bm@Cc@BSE]?q@JK?_@JwA@MQWU]OKk@IgAg@gBcCkCw@oAs@_AWKc@IYBcB@cAESUGWYDW@UCe@AeALkACoA@G@_@G_@Ke@SmAS[K]Es@a@U[_@WyAu@OLY^KZU\\y@nBWz@o@pAgA~Ag@bB]|AYjBC\\Ml@Y`C",
    "resource_state": 2
  },
  "trainer": false,
  "commute": false,
  "manual": false,
  "private": false,
  "visibility": "followers_only",
  "flagged": false,
  "gear_id": null,
  "start_latlng": [
    31.435452,
    119.482461
  ],
  "end_latlng": [
    31.436812,
    119.485256
  ],
  "average_speed": 2.841,
  "max_speed": 3.6,
  "average_cadence": 89.8,
  "average_temp": 30,
  "has_heartrate": true,
  "average_heartrate": 146.8,
  "max_heartrate": 173.0,
  "heartrate_opt_out": false,
  "display_hide_heartrate_option": true,
  "elev_high": 19.8,
  "elev_low": 3.8,
  "upload_id": 2821820900,
  "upload_id_str": "2821820900",
  "external_id": "garmin_push_4000650685",
  "from_accepted_tag": false,
  "pr_count": 0,
  "total_photo_count": 0,
  "has_kudoed": false
}