{
  "resource_state": 2,
  "athlete": {
    "id": 10920812,
    "resource_state": 1
  },
  "name": "晨間跑步",
  "distance": 6008.2,
  "moving_time": 2199,
  "elapsed_time": 3019,
  "total_elevation_gain": 12.0,
  "type": "Run",
  "sport_type": "Run",
  "workout_type": null,
  "device_name": "Garmin fēnix 5",
  "id": 2660660135,
  "start_date": "2019-06-30T22:21:12Z",
  "start_date_local": "2019-07-01T06:21:12Z",
  "timezone": "(GMT+08:00) Asia/Shanghai",
  "utc_offset": 28800.0,
  "location_city": null,
  "location_state": null,
  "location_country": null,
  "achievement_count": 0,
  "kudos_count": 0,
  "comment_count": 0,
  "athlete_count": 1,
  "photo_count": 0,
  "map": {
    "id": "a2660660135",
    "summary_polyline": "w}_pEcjdxSb@MP_@DWA[K[WUQEU?_AJg@?w@D[LQ`@CT@JFTNLRFnBA~@FXEVWJ[?[G]W]IE_@CgANxCtEECk@Ho@Bg@LS?i@IIDW^CPBPBp@Ar@]BWHqA@AAM@m@LIDILCXBbAa@^Rb@ICmA@aBKcANQHG^A\\KJc@BQDoA@[DGKU?KCQWI]Cu@GGyABIBEJA\\BtAApGBzCC`C@fADd@BhEAXId@Lb@@^CtAK|@@b@Cf@@b@I`A@TK^V`@VVZt@MzAHn@C^K`@WXInAEtB@h@H|@Mj@F|AERKFMRK`AK`@B^@bAWfA?XPp@CjATb@Pf@@\\Kn@GH]H@vCTJ@JEL?JJXDXMn@Cf@g@\\[Js@FAx@Fz@A|@BzAHfBF\\Az@Dj@A^JxBEBU?m@EAHSXMDAB@VBBH@NPBj@ArBJ`CDpCABMRAf@Hv@RvD?~@Dx@BdBAjAD\\Kt@AZCnBBZEf@AfACJ@nAGhB?pAA^I`ABf@BzA?ZGADZDxA?pAJbBC|ABl@?fACZBd@Aj@B|@ApA@bAE~ABhCETSH[Cc@Bc@Lg@|@JxACb@Id@Zb@RRPXLLFAPDh@CTLF`AEvBFdLE^Ab@@d@A`DFvCEjCB~CER[BSAO@CP@JJPp@HBRDz@?tCGfBDpBCdB",
    "resource_state": 2
  },
  "trainer": false,
  "commute": false,
  "manual": false,
  "private": false,
  "visibility": "followers_only",
  "flagged": false,
  "gear_id": null,
  "start_latlng": [
    34.247489,
    108.980985
  ],
  "end_latlng": [
    34.253584,
    108.931526
  ],
  "average_speed": 2.732,
  "max_speed": 6.4,
  "average_cadence": 91.2,
  "average_temp": 22,
  "has_heartrate": true,
  "average_heartrate": 132.3,
  "max_heartrate": 153.0,
  "heartrate_opt_out": false,
  "display_hide_heartrate_option": true,
  "elev_high": 403.6,
  "elev_low": 383.8,
  "upload_id": 2821840830,
  "upload_id_str": "2821840830",
  "external_id": "garmin_push_4000670724",
  "from_accepted_tag": false,
  "pr_count": 0,
  "total_photo_count": 0,
  "has_kudoed": false
}