{
  "resource_state": 2,
  "athlete": {
    "id": 10920812,
    "resource_state": 1
  },
  "name": "晨間跑步",
  "distance": 11116.6,
  "moving_time": 4290,
  "elapsed_time": 4754,
  "total_elevation_gain": 9.0,
  "type": "Run",
  "sport_type": "Run",
  "workout_type": null,
  "device_name": "Garmin fēnix 5",
  "id": 7176457358,
  "start_date": "2022-04-03T22:04:31Z",
  "start_date_local": "2022-04-04T06:04:31Z",
  "timezone": "(GMT+08:00) Asia/Shanghai",
  "utc_offset": 28800.0,
  "location_city": null,
  "location_state": null,
  "location_country": null,
  "achievement_count": 0,
  "kudos_count": 0,
  "comment_count": 0,
  "athlete_count": 1,
  "photo_count": 0,
  "map": {
    "id": "a7176457358",
    "summary_polyline": "qxz~D}ugxUDWd@W^Kv@KZO^E|@Fz@Pl@Th@^NDL@x@CTBTGjEkGPOv@sAX[B@|CuEb@a@|@uARUZk@^g@POZo@NYNMf@aAjBuCl@s@x@wAjAiBh@oA|@iB`BiCjAsAh@c@v@u@fAy@v@y@N[AUQq@AWBIHCHSJE^XNPbAvAJBDD@EDT\\l@JJHRn@x@RRBALPN`@b@j@f@f@FLf@`@p@x@h@XVBJD@DF?Pd@JHdAL^P`ANTH@DFBDA\\HVNVBPHVBTLd@F\\RHPZCJHDAf@JLHj@RvANj@Dd@A~@F^CTH^Gj@?hBIdAFbCEb@DJEJ@d@CJDl@BFEFQFB`AKj@B~Ca@dAUhAK|@SVAp@IFEL?tBe@zB]PI~AGh@WRClCUf@QlBSl@Mh@CjBYV?dAWnAKHEFMNKpAGbAQLItAObBYz@GtAWD?@BCJAt@L?hDg@j@O`@AvDo@f@CpCk@P@bASz@?ZMx@OVAh@I`CWj@?~@\\LF?DGd@ITCd@Yv@Bb@Ar@KtAKp@?pAFXAXM|AOf@O|BTH?BGNKt@@@KfABBIn@Ab@@fAHt@FTNZRHn@CnBD~@CRBFFj@BtAGx@RVIz@Cp@MlACn@GNMb@q@Jk@@eAJsBEu@?y@P_FFc@J[DsBQI_AAmBK]BeBZ}@BwAR}Bd@kBTq@Ne@XMREXWfAMdAA`@GTMFKL?|@EIKEo@Tg@VCDwBb@OPOBWXG@OR[Bu@EOD}@j@MX@fACDKGKAOb@QRYLETINqCG_A@a@IsAJkB?oAHEJc@HmCCw@@_BNe@AmLVa@CAG@KYNSHk@Dw@AIACOOTQDkA?mAIuA@gAHaA?m@Jg@Co@FmAG[@[EyAFq@N[?YK]Eo@AoAJSFkEFk@DKDm@Bo@@g@CKHsAHYAyBHmAIg@?c@By@LmAFq@?WESBUAmA@QBo@EmDVOCKBe@I_AFw@Ce@BkBGu@LQCe@FEJSHKAGEUGg@FqAEOFqAHu@Ts@?a@C_@BONIIOFO@KMSBYLa@CMDO?e@Oi@Dg@AqAB_@HQNIKe@J[?gAVk@NONO@g@ZGAi@Zo@ASEUDOCAES?e@Hc@ZK@e@f@iCx@SZYVYf@KBKMUKa@a@KEI@ORSb@ON]l@SL_B?YEg@UQMc@OS@g@M]Aq@ISB",
    "resource_state": 2
  },
  "trainer": false,
  "commute": false,
  "manual": false,
  "private": false,
  "visibility": "followers_only",
  "flagged": false,
  "gear_id": null,
  "start_latlng": [
    31.435773549601436,
    119.4839929137379
  ],
  "end_latlng": [
    31.435048263520002,
    119.48454586789012
  ],
  "average_speed": 2.591,
  "max_speed": 4.508,
  "average_cadence": 94.2,
  "average_temp": 19,
  "has_heartrate": true,
  "average_heartrate": 140.9,
  "max_heartrate": 155.0,
  "heartrate_opt_out": false,
  "display_hide_heartrate_option": true,
  "elev_high": 6.4,
  "elev_low": -2.0,
  "upload_id": 7641714212,
  "upload_id_str": "7641714212",
  "external_id": "garmin_push_8862505910",
  "from_accepted_tag": false,
  "pr_count": 0,
  "total_photo_count": 0,
  "has_kudoed": false
}