{
  "resource_state": 2,
  "athlete": {
    "id": 10920812,
    "resource_state": 1
  },
  "name": "晨間跑步",
  "distance": 10090.7,
  "moving_time": 3592,
  "elapsed_time": 3612,
  "total_elevation_gain": 118.4,
  "type": "Run",
  "sport_type": "Run",
  "workout_type": null,
  "device_name": "Garmin Forerunner 245",
  "id": 7176447049,
  "start_date": "2021-02-01T22:02:34Z",
  "start_date_local": "2021-02-02T06:02:34Z",
  "timezone": "(GMT+08:00) Asia/Shanghai",
  "utc_offset": 28800.0,
  "location_city": null,
  "location_state": null,
  "location_country": null,
  "achievement_count": 0,
  "kudos_count": 0,
  "comment_count": 0,
  "athlete_count": 1,
  "photo_count": 0,
  "map": {
    "id": "a7176447049",
    "summary_polyline": "qwz~DqkgxUE[@YA]BO?eCDc@C[@m@CWBQNGdBY~@?lAHh@NlAt@\\\\`AlAx@x@h@`@b@Nl@~@p@l@n@x@PPTHh@b@hAb@\\GTFnAHf@?v@LR?XEh@HLCROVCVN\\@BHLPj@Zv@x@^Lp@CNSTOXi@Lk@BYFQD_@Ve@Xy@JKNCXA\\HXV|@f@ZTb@f@Vf@DVHDHVLL|@h@VDd@ANKl@sANa@Xi@J[@QVo@NKRBd@MRo@X]JAJRQVEJGd@BN@JLPXPVBtA@~ACNKLOHWCo@ISKOWM[Cq@DsB@MBKJKPGZB^DTHLTN`AB`CGZMNQBS?i@IUIKa@SOA{AFiAAUHQNGXAPBb@DLPRTJfBBzAENKR[BK@WAQIUSUOIWEeD@SFSTKd@@ZBNNVJHXHZ?bDEROJQDSAa@GUMS[QUC}C@e@NKNET?XD\\PZTJb@FxCERGPMJY@]EWKWSQg@IaDBSFQPIRAT?PDT\\d@`@FjDCLCPSL[?YIa@OUUOYEkC?a@DUHUh@C^@RJXXTVDzBA\\CZ@JERSLYBUA[ESUYQKKCcAHoB@QFSNIREV?TF\\JNVLTBrDEPGTODIBO@c@I[GMUUe@I_BH}@AQBSJW`@EVFl@HLJL^HfAElB@PELGNUDU@]AQEMWYUIkDBc@HSLKV?r@HRJJf@R`@@jAC|@@\\SNOHU@SCUO_@MOWKeDF]DOHMPGVAHFj@FNJJXH`DAb@EPINSFO?_@Mg@IMQOOCcDBYDSJSXET@\\BPLP^TpABtBCLGPUJq@CQIUQWSIWCoDFIDQPM`@CPD^NXf@TfB@jAEZOHMJYBUK_@MSOOOGuA?_BCWJONIPE\\B^LXPRRFjB@lACVKPOFOBc@E[Sa@QMMCiB?mAFUHSPGNAXD`@FPTXNFN@dCCl@GVOHMDOAQBKEYQ[YSWAiD@[NMJITCVFf@LTNNRHnAAh@EfA?RIPSHe@?QAQWe@QKOCqCDc@G_@?UJO\\I\\EHIDs@BSDa@GH}@CkA@WO_AA{@@WCM@YCSKWCk@@]Ke@@m@EMAYBo@DOCc@Ic@EK[Mi@As@HUEQDMAYDSAOD[ASBm@BYCKBUPKB_@?KEu@DcA?i@FaBC{AXWJ_ADSHsARc@By@NQCMUMEI@u@b@K@q@b@wAh@_@V]LyBtCq@t@IRYVENY^IBQEc@g@m@y@AKW[SOO_@m@[",
    "resource_state": 2
  },
  "trainer": false,
  "commute": false,
  "manual": false,
  "private": false,
  "visibility": "followers_only",
  "flagged": false,
  "gear_id": null,
  "start_latlng": [
    31.435618735849857,
    119.48233413510025
  ],
  "end_latlng": [
    31.434209905564785,
    119.48441435582936
  ],
  "average_speed": 2.809,
  "max_speed": 3.956,
  "average_cadence": 91.6,
  "has_heartrate": true,
  "average_heartrate": 148.3,
  "max_heartrate": 170.0,
  "heartrate_opt_out": false,
  "display_hide_heartrate_option": true,
  "elev_high": 16.3,
  "elev_low": 5.1,
  "upload_id": 7641703091,
  "upload_id_str": "7641703091",
  "external_id": "garmin_push_8862494613",
  "from_accepted_tag": false,
  "pr_count": 0,
  "total_photo_count": 0,
  "has_kudoed": false
}