{
  "resource_state": 2,
  "athlete": {
    "id": 10920812,
    "resource_state": 1
  },
  "name": "ć™¨é–“č·‘ć­Ą",
  "distance": 13141.7,
  "moving_time": 4714,
  "elapsed_time": 4763,
  "total_elevation_gain": 19.0,
  "type": "Run",
  "sport_type": "Run",
  "workout_type": null,
  "device_name": "Garmin fÄ“nix 3",
  "id": 7176187600,
  "start_date": "2016-11-24T21:04:35Z",
  "start_date_local": "2016-11-25T05:04:35Z",
  "timezone": "(GMT+08:00) Asia/Shanghai",
  "utc_offset": 28800.0,
  "location_city": null,
  "location_state": null,
  "location_country": null,
  "achievement_count": 0,
  "kudos_count": 0,
  "comment_count": 0,
  "athlete_count": 1,
  "photo_count": 0,
  "map": {
    "id": "a7176187600",
    "summary_polyline": "_uz~DelgxUf@?jBJ^MrAiBv@mABWMm@@[h@n@dAz@X^z@x@VPP@j@f@NTTRLZp@|@v@j@p@Rn@H\\Cf@AV@^N`@HNEd@@PDDAd@B`@GT@~@Zb@Xd@@x@f@`@`@^R\\`@XNr@|@dAdAd@ZNVh@j@\\Tj@RTGNKl@eATcAPe@l@kANg@^w@JGRCDEd@gAD]x@}ADSBGBYLQJCNBBHPNNFDFAJL\\NPHDvDGvADLCFIF_@A}@DWEe@?_@MQMEk@I{AA{@D}@AGBGNa@lB@SLk@\\m@j@@bEEAEICo@Gu@?s@FkA?c@jAQ~@Lv@JNJFnA@|AClBDhCIhBFhBf@DDpAVrAZ^NjBPt@@f@L`ALdCj@f@Br@N\\AJ]V{B@[`@aC@g@Du@F_@PiBPq@@iBFe@Lg@RcB@]Lc@RaBB_AL}AAULg@L_A@i@VoADq@XaB@KEe@d@mD@OCs@@_@^yAB{@Jw@ZgBFeANaBNy@Bc@Jc@Da@TwA@g@NeA@g@RwBHmBVy@@YH]Ai@Pw@Be@NiA?{@Jy@BiAHw@DeAPqANw@?]MQRCDIXgCRyBDmALsAN}@NqBv@gG@m@PgAL_BCWSQa@IuDHWBeAEmB@uBRiFAkBLoBD_EEcALoDR_AKuA@_HXs@C{BD_CIyETmBAgCJm@AgBBeAFgCGqB?e@Ds@Ai@BwAMcA?aBOYBm@Cm@MuAHaAMeF_@w@L}AIaAM_CMgD[q@AsAKaBKkAAqH]k@MuBIOBgB?}@KZFjCAhAD`BR~FRfARdCR|BDtI`@JBXRJTTr@P|AHh@JhCRfCNz@@p@RzA@dANd@D^?j@DbBH`@Df@Lb@NfABDA^@\\PbABb@G|AD^?z@FTTVNrA@l@JpA@d@CPQDEFAb@BVAPWTsAr@sBdBaBlAaAhAu@b@u@`A{ArAs@vA[z@ILy@`AuAfAyBbAm@r@a@Bm@h@s@\\_AX[DcA`@s@@oBNc@NWVKVCn@GD?D?XKPCP@RU`@AJHbBGnBOtAMt@I|AU~A?VMbA?NKfAE`AGb@Ez@_@nC@LI|@ERK\\Gb@GjAA`BIdAKn@Cd@YjBEn@?FNL^@zBO|AExAQp@Fd@AlBa@tCMxCJlAXXAxAP",
    "resource_state": 2
  },
  "trainer": false,
  "commute": false,
  "manual": false,
  "private": false,
  "visibility": "followers_only",
  "flagged": false,
  "gear_id": null,
  "start_latlng": [
    31.435207184404135,
    119.4824331253767
  ],
  "end_latlng": [
    31.435871198773384,
    119.48075766675174
  ],
  "average_speed": 2.788,
  "max_speed": 4.926,
  "average_cadence": 92.4,
  "average_temp": 21,
  "has_heartrate": true,
  "average_heartrate": 142.1,
  "max_heartrate": 176.0,
  "heartrate_opt_out": false,
  "display_hide_heartrate_option": true,
  "elev_high": -17.4,
  "elev_low": -28.4,
  "upload_id": 7641421294,
  "upload_id_str": "7641421294",
  "external_id": "garmin_push_8862221249",
  "from_accepted_tag": false,
  "pr_count": 0,
  "total_photo_count": 0,
  "has_kudoed": false
}