{
  "resource_state": 2,
  "athlete": {
    "id": 10920812,
    "resource_state": 1
  },
  "name": "ć™¨é–“č·‘ć­Ą",
  "distance": 15580.4,
  "moving_time": 5982,
  "elapsed_time": 6215,
  "total_elevation_gain": 24.0,
  "type": "Run",
  "sport_type": "Run",
  "workout_type": null,
  "device_name": "Garmin fÄ“nix 3",
  "id": 7176186398,
  "start_date": "2016-11-19T20:59:07Z",
  "start_date_local": "2016-11-20T04:59:07Z",
  "timezone": "(GMT+08:00) Asia/Shanghai",
  "utc_offset": 28800.0,
  "location_city": null,
  "location_state": null,
  "location_country": null,
  "achievement_count": 0,
  "kudos_count": 0,
  "comment_count": 0,
  "athlete_count": 1,
  "photo_count": 0,
  "map": {
    "id": "a7176186398",
    "summary_polyline": "{uz~DelgxUXGx@Px@Bt@GR[XGxB_D@e@IMKc@JGTVBPf@f@^h@x@n@R`@b@^n@Z|@x@Ph@jApAb@PzANh@BVEt@Vp@G|A?jAJX\\dChAhAv@t@x@NVLHNV`Al@rApAZf@b@PJ`@F@F}@N@NOn@{ALq@rAwBp@_BhAmBNk@b@aAHk@r@Q^VTEN]\\kACCGBHTOb@Cb@DT`@j@ZJd@BbC?TKXa@Ls@E[QY[UQCaDB_@LUXO`@Er@FZTTXFtD@ZIPMVk@D[Gi@U]WQ_@I}BBmAE?GHCbELbA?L\\G~@HR?lAFLd@HdB?rC`@v@NpAf@zGt@|Ct@tAPhBd@rBZn@T\\?TF`@XnANh@VVCrD`@hHvA~@H~Ex@r@XlAFnA`@|AV|Bt@pCNzAXRJx@BTLrAVnD^fKBtCEbBTrAE^BfAMt@FlAE~ANnCSpBBbBIvCCnLF|@H~@KbA@b@E`AJjAGnA@t@[rEOl@On@g@R[Nw@CwADiAF]DeDAKNoA?m@Hs@@cCHwANsHL{BDwER_G@e@Mq@\\uDTyEJy@BuBJgEJiBGQGENcA@eAZ_ECuBJiB@qASi@QOa@MmCWsCSuBHsGz@}GjAoD^oD|@eBLcCf@yCPeB^{CXuB\\mAGc@BmB~@cAXmEh@oCRQFGLUFsAFq@TOVMvAKn@Wj@KpA?lAMlABnAOz@Er@?|@Dd@IvA@jAEt@?`AWrDOn@BNGv@Hl@GJG\\HNJz@UlB?^Q|@@ZSzAA`AH|AIvAGZArAW~B?|@EP@x@?lBWbBFhBSbAB\\Cn@ITeG{AcDWeE_Ai@Em@Ok@YgCQuD}@yFu@[Ma@CuA[]?gAc@mEq@oBa@}@[qA?gEi@eBa@_BSk@Sw@G{@WcAKQKmAOUOqAYoAFsFCmAFuAIOKKSQg@A[Hk@T]On@Ef@F`@TZt@TrD@XSPYHU@UE[KYSWSKeE@a@b@KXEb@Pn@f@\\bB@`BGROTa@F]?c@GSSWYOSAuDBa@`@Up@Dn@NT^RzAFhBAXQT_@Fe@Gc@Q_@WS_EBWFSVMd@Fv@NTZNZFfD?XSZm@Be@CY_@g@wDEe@Ci@`@Kv@Jt@\\VjEH`@WZo@BUIm@WYSKeEBg@b@Ul@Nt@b@^fCHbAC^WN]BY",
    "resource_state": 2
  },
  "trainer": false,
  "commute": false,
  "manual": false,
  "private": false,
  "visibility": "followers_only",
  "flagged": false,
  "gear_id": null,
  "start_latlng": [
    31.435339953750372,
    119.48243480175734
  ],
  "end_latlng": [
    31.422325959429145,
    119.48235877789557
  ],
  "average_speed": 2.605,
  "max_speed": 5.578,
  "average_cadence": 91.3,
  "average_temp": 20,
  "has_heartrate": true,
  "average_heartrate": 132.9,
  "max_heartrate": 178.0,
  "heartrate_opt_out": false,
  "display_hide_heartrate_option": true,
  "elev_high": 17.2,
  "elev_low": 9.4,
  "upload_id": 7641419950,
  "upload_id_str": "7641419950",
  "external_id": "garmin_push_8862219886",
  "from_accepted_tag": false,
  "pr_count": 0,
  "total_photo_count": 0,
  "has_kudoed": false
}