{
  "resource_state": 2,
  "athlete": {
    "id": 10920812,
    "resource_state": 1
  },
  "name": "午後跑步",
  "distance": 5008.8,
  "moving_time": 1651,
  "elapsed_time": 2372,
  "total_elevation_gain": 37.6,
  "type": "Run",
  "sport_type": "Run",
  "workout_type": null,
  "id": 7176200331,
  "start_date": "2015-08-07T08:43:45Z",
  "start_date_local": "2015-08-07T16:43:45Z",
  "timezone": "(GMT+08:00) Asia/Shanghai",
  "utc_offset": 28800.0,
  "location_city": null,
  "location_state": null,
  "location_country": null,
  "achievement_count": 0,
  "kudos_count": 0,
  "comment_count": 0,
  "athlete_count": 1,
  "photo_count": 0,
  "map": {
    "id": "a7176200331",
    "summary_polyline": "sttsFc{ofUFBPlABGOUAOCADr@N?DPADDBEF@PCIDFFp@?TEBNKLJZb@TNZJb@DFAP?DEPGBED?DGf@KDGTKf@GXIDALHj@B`@E`@INAn@UPCL@LFv@?x@_@dASXQV[HHH?j@ONIRYtF|@VE\\?PCB@~E}BFSJGGSJcA?Y@OCU?YEY@QFe@V_ATiAP_@B?JBBATi@LUb@[NGVE@EASAEB]@}AEy@E]@o@Ci@Mo@M}ACs@I]Ck@QGGUIBPUTeAHMZQd@AVOd@GZMx@En@MhAIvA_@p@Ej@G`@UXG?DF@@BAB?DXj@JZRZ?FNZtAxAj@`@f@TJJHDTHVB~@Zt@LFFb@CVBvA^p@FNFBFHBD?BCRCJDV?^B`BCN@h@?f@Bx@Mp@ALMrA[b@@p@A~@H^@XGF?^_@LATKD?LDr@I|@Lx@D`@IJ@RIFEJCNAv@UbAFhAGTMRCN?h@CNBr@ABENCh@Bf@OTUV?LEv@Dl@ELE`@Bd@G\\Aj@M|@K`CERMz@QXWTANCVK`@UD?LCdADRDLDZBhCDPCJMp@OFCx@?TEZA~AYVGFKNELM^Mr@A\\DTETBZ@VIt@GPGN@NBG{@BALBFAZK|@QLCRM`@Ix@[XYZQt@m@LSNc@FGb@o@^WDKJCAAD@NHRX`@?\\QZYPWHE?IBUA]D_@H_@LYJk@L_@ToA@o@D[AKDG?@NC@@T@d@Gp@Ar@KZA",
    "resource_state": 2
  },
  "trainer": false,
  "commute": false,
  "manual": false,
  "private": false,
  "visibility": "followers_only",
  "flagged": false,
  "gear_id": null,
  "start_latlng": [
    40.08794339373708,
    116.57666634768248
  ],
  "end_latlng": [
    40.05252021364868,
    116.5884461067617
  ],
  "average_speed": 3.034,
  "max_speed": 10.586,
  "average_cadence": 85.2,
  "average_temp": 28,
  "has_heartrate": true,
  "average_heartrate": 151.1,
  "max_heartrate": 162.0,
  "heartrate_opt_out": false,
  "display_hide_heartrate_option": true,
  "elev_high": 47.8,
  "elev_low": 28.2,
  "upload_id": 7641435146,
  "upload_id_str": "7641435146",
  "external_id": "garmin_push_8862234153",
  "from_accepted_tag": false,
  "pr_count": 0,
  "total_photo_count": 0,
  "has_kudoed": false
}