{
  "resource_state": 2,
  "athlete": {
    "id": 10920812,
    "resource_state": 1
  },
  "name": "晨間跑步",
  "distance": 11029.8,
  "moving_time": 3490,
  "elapsed_time": 3569,
  "total_elevation_gain": 6.0,
  "type": "Run",
  "sport_type": "Run",
  "workout_type": null,
  "device_name": "Garmin fēnix 5",
  "id": 7176392282,
  "start_date": "2019-12-01T22:04:33Z",
  "start_date_local": "2019-12-02T06:04:33Z",
  "timezone": "(GMT+08:00) Asia/Shanghai",
  "utc_offset": 28800.0,
  "location_city": null,
  "location_state": null,
  "location_country": null,
  "achievement_count": 0,
  "kudos_count": 0,
  "comment_count": 0,
  "athlete_count": 1,
  "photo_count": 0,
  "map": {
    "id": "a7176392282",
    "summary_polyline": "ilv~DimgxUG^BHTABBEXF`@OXLnBNTRHFLS`DEpAKl@?dAMdD?RY|CStAEf@MzBGvCALOV[F]ECBu@OSOWEyAEaBk@}Bo@m@IwA]wAI]SQc@?_@TiAHq@?MCIm@][KaAUaAG[OcAUuC[g@FONWd@CPOd@CZ@^ALGFQLs@Im@@{AOqBk@cAQw@GYMY[_@Ee@HWAk@Qw@MYMqBc@cA]OAqA_@kAAo@Ha@a@K_@AKBGlBsDA[@Gt@wA`@oAd@_Ah@wAf@cCFCRDz@e@ZcANC@B?FQVM`@AJB\\FVXZ^NxC@`@Cb@MT_@@i@Gq@KO]Uo@Ge@DoAE_@B]JUXO`@?j@Nd@`@V`@FxCBHCX?RGR_@Dm@E{@U[_@QeEFa@PSZK\\?j@FNJNb@V\\Fz@BbBEd@ITOL_@@[Gy@OY]QcACqBF{@XQ\\Ef@Df@TZj@RvC@`@Eb@?POHk@@c@E]O[OQYMMCsCDg@H]PS\\CJCP@h@JVLPl@PbAC|@Fv@G^OVg@Fk@Ig@SYa@S_@C_DL_@LU\\Od@?j@X^^NpDH`@AZMP_@J{@Ag@W]g@S_BDq@Em@FYFWRKZKf@B`@T\\b@Pf@FnAB`ANn@ENOHe@BgAKg@UYYKkAAaCFYPORWr@Dh@VX`@RhDJb@F\\CRYJeAAm@O]QW_ACuBA{@PGDS\\Mj@?`@P\\`@VdAHjDCNWHe@?k@Eg@S]WOa@C_C?}@JIHGCGDOXOl@WDOCWc@IsADYAUEAj@EZSp@EPGSFz@Er@D~@KhBEhAO^IRQh@Ab@OnADj@StBAjAJt@Xl@LX?PIJKZwCVsANqBAUNiC\\STa@JE^B`@K~@AROxAIf@IxBPh@Af@HrD\\^Oh@AvAMFa@R_@b@S`@@TRHBX\\z@PVKJB\\?|@IHFDJGLKj@Ch@Az@KvB@zAK\\S`DKf@OXEj@Aj@Mx@EbA@t@ALFn@MlBMl@GtAOlAG|AGTGBYGcAE]GwAIe@IGO_AK_A[uAQIEc@@i@Oq@]e@KMK_@m@?[RcAf@mFGiAX[Ta@bAYFEl@GnAEtE?FCd@@JCrAF^HvA@JV?TYlBNVSnBIfBSl@C^BL@k@IWiBMOEAEGcAKc@CY@[DEx@IJQ@O",
    "resource_state": 2
  },
  "trainer": false,
  "commute": false,
  "manual": false,
  "private": false,
  "visibility": "followers_only",
  "flagged": false,
  "gear_id": null,
  "start_latlng": [
    31.413333686068654,
    119.48261702433228
  ],
  "end_latlng": [
    31.413409374654293,
    119.48250805959105
  ],
  "average_speed": 3.16,
  "max_speed": 6.022,
  "average_cadence": 89.4,
  "average_temp": 10,
  "has_heartrate": true,
  "average_heartrate": 163.0,
  "max_heartrate": 189.0,
  "heartrate_opt_out": false,
  "display_hide_heartrate_option": true,
  "elev_high": 7.4,
  "elev_low": 0.0,
  "upload_id": 7641643203,
  "upload_id_str": "7641643203",
  "external_id": "garmin_push_8862435890",
  "from_accepted_tag": false,
  "pr_count": 0,
  "total_photo_count": 0,
  "has_kudoed": false
}