{
  "resource_state": 2,
  "athlete": {
    "id": 10920812,
    "resource_state": 1
  },
  "name": "ć™¨é–“č·‘ć­Ą",
  "distance": 13132.9,
  "moving_time": 4475,
  "elapsed_time": 5343,
  "total_elevation_gain": 163.0,
  "type": "Run",
  "sport_type": "Run",
  "workout_type": null,
  "device_name": "Garmin fÄ“nix 3",
  "id": 7176370010,
  "start_date": "2017-08-30T21:56:30Z",
  "start_date_local": "2017-08-31T05:56:30Z",
  "timezone": "(GMT+08:00) Asia/Shanghai",
  "utc_offset": 28800.0,
  "location_city": null,
  "location_state": null,
  "location_country": null,
  "achievement_count": 0,
  "kudos_count": 0,
  "comment_count": 0,
  "athlete_count": 1,
  "photo_count": 0,
  "map": {
    "id": "a7176370010",
    "summary_polyline": "}pcaDm|`jSJULEG\\vAhCUl@gCxCaAh@`@GNOd@Aj@c@TBt@v@M~@^Dr@Yb@[n@Vp@g@NFlA_@nAs@DDIRgBhDAJv@r@n@Vv@Yh@Le@]v@AxAiB`AM~@bBGHLN]rAbBq@l@FdAkAUnBJh@PFj@WF_@YeAGg@Z_@XgAf@?aB_@YLFUb@U[pA?^LNnD}@xAm@UbAd@L`FuAEj@JTTJKNFBEXIBKKbAcBb@a@^UdC]RSzAX@`@r@OrABCvCD^JJdB\\d@sAtA_@HSHLx@L@LhAt@?NX\\GZHPjA\\hB?HSpCiB|A_BbDqBjD_ApBWrADpAO`@a@zBaAn@oA`Aw@r@UVh@`@Lj@a@r@y@VBXVFlA`@xA[bBR|CO~ADh@Vd@lAfAjBv@f@b@^v@PvAx@pAD`@AdA{@hAw@tBw@lCSrBC~ARp@?l@q@jCMdAFl@CbBn@vCbAjAOL^Et@t@fCjA`@b@bAxAdBzDv@bA~CZrA\\dAt@dBtDx@l@^NpGd@jBBXR@`@]ZgAGwBRuASqAL{@_@sAf@_@^BvEThBDMa@sCCqAD]T[CIe@?w@c@o@I_Bm@WF]d@s@PeAHwAMkJ{EK_ADPrA[fAe@dDeAt@BdAq@f@MVc@aAgBiCeFu@s@oBw@gA{@_B_ESwBCuAj@qEMcD^_DLw@d@uAj@uAt@kAHsA]_Ag@e@UsAYq@k@m@}CyBu@oAA_@VqAWaC\\uBa@qAKgAs@sAOuAb@sArAkFNWtA}@nAwBXuAM_@QDOnA]jA]j@gA~@wAzCkAzEJdBEXcAbA[RS?]Sa@c@mAz@uAfB{Ah@_@ZwCGw@Ly@b@yDv@m@TiBrAU`@yBhBmChAcADmEg@_Ae@CYe@JYIa@u@]Z}@M}Ac@IJg@?{@W_BeAwAQ][m@`A{@d@c@cAQaAIDSMGLGKWj@w@\\sAIsAm@w@AaAEqA_AaBa@g@uAmAGWSkAH_@GEU[SM@OSgBm@o@GW[?QUI}BR_@[m@cA}@v@YBc@OM\\OU{@SGk@a@j@]AWYAgASq@_@[{@MKOMCBPMIg@Fm@v@EXR\\t@y@HHIl@^TVCz@t@PAt@g@LHHl@b@jAZQJJJQJXDEB\\R_ABV^TXj@|@X",
    "resource_state": 2
  },
  "trainer": false,
  "commute": false,
  "manual": false,
  "private": false,
  "visibility": "followers_only",
  "flagged": false,
  "gear_id": null,
  "start_latlng": [
    26.565438034012914,
    106.66967270895839
  ],
  "end_latlng": [
    26.56456765718758,
    106.66965737007558
  ],
  "average_speed": 2.935,
  "max_speed": 11.736,
  "average_cadence": 91.2,
  "average_temp": 26,
  "has_heartrate": true,
  "average_heartrate": 138.9,
  "max_heartrate": 168.0,
  "heartrate_opt_out": false,
  "display_hide_heartrate_option": true,
  "elev_high": 1189.0,
  "elev_low": 1122.4,
  "upload_id": 7641619214,
  "upload_id_str": "7641619214",
  "external_id": "garmin_push_8862411760",
  "from_accepted_tag": false,
  "pr_count": 0,
  "total_photo_count": 0,
  "has_kudoed": false
}