{
  "resource_state": 2,
  "athlete": {
    "id": 10920812,
    "resource_state": 1
  },
  "name": "晨間騎乘",
  "distance": 51673.1,
  "moving_time": 7026,
  "elapsed_time": 12084,
  "total_elevation_gain": 234.0,
  "type": "Ride",
  "sport_type": "Ride",
  "workout_type": null,
  "device_name": "Garmin Forerunner 255",
  "id": 7540083661,
  "start_date": "2022-07-27T20:05:44Z",
  "start_date_local": "2022-07-28T04:05:44Z",
  "timezone": "(GMT+08:00) Asia/Shanghai",
  "utc_offset": 28800.0,
  "location_city": null,
  "location_state": null,
  "location_country": null,
  "achievement_count": 4,
  "kudos_count": 0,
  "comment_count": 0,
  "athlete_count": 2,
  "photo_count": 0,
  "map": {
    "id": "a7540083661",
    "summary_polyline": "qwz~DumgxUHeCKD@oEjCe@dBPfBr@lD~D`IbHrA`@jBLl@RN\\MjEiB~B{@rDL~IAVULVjDEdF{BdKkA|BkA|ODh@^^~MbB^VBv@a@zQe@bI?lKJbEUrLFf^_@v]qBjXoBdTm@xPCnGz@jUdB|P`BnJtJbd@Dp@|@~C~AtJx@xIx@lUNrNZxH?jE[hK@jNP`GJzYZ~U`@lWb@zKbXzArFp@`CWrDeAhDEtHtA~HElBNfA\\rBnChBdAfF`@tNvKrGxCCf@lExM\\jFSvKuEbMdDhBdPxMdJdJlArCr@zGdA~DCd@aBz@uEfAYr@a@zDyC`CVbKzANbJ[pJFdCbCtAxEpGzEzEj@dFrDj@GhDcBn@H~L~T@\\UVuBx@MbAHZlBhAbDp@jAjAv@~AFhKjFjEpBHpBy@`BiCdDiJnDgDp@uCzBw@`@CRRAi@|FmAYYLPa@y@JZ`yAbFSYuEGiEqCqBk@eOa@OOCsBQ]gCIyFmCgAKaCl@{ChCaAb@cLWyStFkCbAHHnL{DtJaCtLPpAk@rCoCpB]bAPdEzB|Dd@PZC`B`@^nLTDVIc@ANtA?bAXxFjDxIXvB}@pB}BdA{Bh@e@bCw@tSuJfJgCxDDrBl@xEzBdEz@bDBfLgDvA@rKdB|LU`Ii@zEi@vScFxGY|EBt@g@ZiBb@IvHHvFd@zE|@xH`CxRqBPqEg@qDAqG`@oF`AkGbAqP_@c@sCu@iI_AYu@z@sBIwEk@kDaAwCgAm@gCJuDs@eG@_@a@W_Ak@_E}CmC_AeB]wCO_Q^{CpCeMImCZ}AEuBUo@kAi@iGW_EkAaGT{Bu@KSkCkTOqEyAsQc@gJsA_OD{@\\kApCoDTaBmD{IwB}Bo@uAeBeKYIwA|@_FsAwCVwD`D{TzI_CfDkD~GuAtA{Br@mDPYS|AqLlCmGz@aFfGsa@LcDPy@lDoHlC_I`AYpLVdAMf@g@l@oCCw@o@mAyAuAsD}Bq@oAB{@oDc@uD_Aqt@{VqMaDwLiBaQ_A_PHkPdAwJTsN_@sLmAoI_BaHkBma@sOmPkFqf@kKyM}BiMeAwKWqg@l@aFb@qHGoT^Eg@fVo^pV{\\bCuEhBqFfAyFh@eGnCwo@h@qJTm@K{@x@sVEp@^kIg@]iCW{Tw@kk@cDMYjB}]y@]@s@MSmTkDcJoBOe@D{Cl@aQKg@]]_VkIwRyB_UnA_NWMc@HqBp@cDtGaMEm@{@q@zE_Iq@OmDBSE?U",
    "resource_state": 2
  },
  "trainer": false,
  "commute": false,
  "manual": false,
  "private": false,
  "visibility": "followers_only",
  "flagged": false,
  "gear_id": null,
  "start_latlng": [
    31.435613287612796,
    119.4826783798635
  ],
  "end_latlng": [
    31.435559559613466,
    119.48257679119706
  ],
  "average_speed": 7.355,
  "max_speed": 12.676,
  "average_temp": 29,
  "average_watts": 140.2,
  "device_watts": false,
  "kilojoules": 985.1,
  "has_heartrate": true,
  "average_heartrate": 63.8,
  "max_heartrate": 90.0,
  "heartrate_opt_out": false,
  "display_hide_heartrate_option": true,
  "elev_high": 32.4,
  "elev_low": -20.6,
  "upload_id": 8040317929,
  "upload_id_str": "8040317929",
  "external_id": "garmin_push_9287544454",
  "from_accepted_tag": false,
  "pr_count": 4,
  "total_photo_count": 0,
  "has_kudoed": false
}