{
  "resource_state": 2,
  "athlete": {
    "id": 10920812,
    "resource_state": 1
  },
  "name": "晨間跑步",
  "distance": 7777.5,
  "moving_time": 2995,
  "elapsed_time": 3270,
  "total_elevation_gain": 6.0,
  "type": "Run",
  "sport_type": "Run",
  "workout_type": null,
  "device_name": "Garmin Forerunner 255",
  "id": 7550342547,
  "start_date": "2022-07-29T21:26:19Z",
  "start_date_local": "2022-07-30T05:26:19Z",
  "timezone": "(GMT+08:00) Asia/Shanghai",
  "utc_offset": 28800.0,
  "location_city": null,
  "location_state": null,
  "location_country": null,
  "achievement_count": 0,
  "kudos_count": 0,
  "comment_count": 0,
  "athlete_count": 1,
  "photo_count": 0,
  "map": {
    "id": "a7550342547",
    "summary_polyline": "kiu~DmhixU`@@RBLIHCP?JGfAKLEz@Mj@A\\Cj@SX@LHGxBBj@Cj@QnDC|@KzBBb@HR?JElAGrCEZGrADX?f@HJRHn@CHDvCK`@B`A?lAEv@?nCErAGd@@TANH@H_@~@Qt@HYR[XeALQ~EKlCBXAz@Dd@CFIF{@H[`@g@P_@VSHKPg@@QJ{C^kGLkEZaEDyBZqCJ[LQj@OtBa@j@Eh@OpB[ZIn@EhASx@E~A_@lAOpDm@|AOZ?t@IvB?|Ef@PFJHPXDPOpGW~GCxAI|AGjBGp@Ex@?~BIxA?`@OlAG|AK`@MLIDq@Bo@AqBJ{A@kACkA@qBKgA?cAB_@Cu@Da@?cAFSAu@B}FDkAAaAIcAAQEQKMSEUEi@?a@TwFPeCCA@UDoADm@FWNMTIv@K\\Id@El@MpBYhB_@x@G`@Kx@ET@`@CdAHfADLBFH@HAn@Gh@?\\IzAQpFEd@ChBG\\M|ACLQ\\ONQJUBu@@mAJeEB{@AyA@yAE]EqACc@HY?UAo@IsCVwAD{B@uAHgGDoADiDDs@Bu@HcADG?@EiDHKGIMIUASXkGFsERuDJwDHwAAOEGEAcCViATu@FYHoAP[F]R_@BNE",
    "resource_state": 2
  },
  "trainer": false,
  "commute": false,
  "manual": false,
  "private": false,
  "visibility": "followers_only",
  "flagged": false,
  "gear_id": null,
  "start_latlng": [
    31.407747650519013,
    119.4920729007572
  ],
  "end_latlng": [
    31.407972620800138,
    119.49196016415954
  ],
  "average_speed": 2.597,
  "max_speed": 3.996,
  "average_cadence": 91.0,
  "average_temp": 30,
  "has_heartrate": true,
  "average_heartrate": 139.6,
  "max_heartrate": 161.0,
  "heartrate_opt_out": false,
  "display_hide_heartrate_option": true,
  "elev_high": 8.2,
  "elev_low": 0.4,
  "upload_id": 8051706192,
  "upload_id_str": "8051706192",
  "external_id": "garmin_push_9299662218",
  "from_accepted_tag": false,
  "pr_count": 0,
  "total_photo_count": 0,
  "has_kudoed": false
}